[
    {
        "gameID":"NA1_4861935017",
        "gameVer":"13.24.547.9214",
        "gameDurationMinutes":"30:03",
        "gameCreationTimestamp":"1702750048128",
        "gameEndTimestamp":"1702751869603",
        "participants":"[\"MhhPmRjYrChRh8d8MoLh73HmM6JgaMispQyw5ptooO_yxAUsw1TxRHdVHCE09o4ViRCjac6Bo6Ek8A\", \"ZqD-OEyqVB63gchjUojc3Wkcs4wLHvmGW3ZWnyDE_7Am1InnOS4x1ZtHi_6PINSLRMLfM5ntCVzTcA\", \"K98iyuDBR8uxwPa9oV82iOXP4DQFwtbL7Wu4fOlk_mpK3HpAxr7af_-aykzxP8OFN9B6gbdQDEW11g\", \"uVKUoWtMeZ5S9nrvX1UKdbdzAJc67VCPK7y2fZxUzbl0zIgPuRg7nASZ6-ofhWZ8IVGOy6imDSihGA\", 
\"cf6OijZvpvEpOSYX1igxKWcmuDqzTeHjEOALsmybIHxzUoR28z5c4BXAbc68Rd3A92UkhErTWdFa7w\", \"6ametUo1Iqtk_TVMguwBaHpjbdhmxZcc0ELVe4Aw5o8_9Qs0TV7sYHcXN2xKL2UHDOWXTcJGvIXpfw\", \"uEzMyB5WdmuEGVd6jiUb0XpTXIHjNPHQ2bJdBlSiSJN6iJjlT-jorexAfCrsJ51qbUrcIYfC8mjf-w\", \"3QoQIahaLadkPys5y8WzJ3dBYCGaeonBEFDOEX6utUW9_L3n9cN6IMN49-wnfn_HwahMJPhVfxr_vg\", \"Yn7VuH9yXRQt02nHQL43l_aJXhP-2p0XrSkd_a3OPQ5DxV8cUWbYJDb3zR0euaJKNDNDqbLO4ksBpg\", \"Wxo1NwPfZcKlVCXSDGPvcc6W1J0c27wBmne8Yls9oyFfX7DwTH6-G5TAzbe3C2TxpbNoD8Fn7ZpHZg\"]",
        "matchdata":"[{\"Champ\": \"Warwick\", \"kills\": 13, \"deaths\": 8, \"assists\": 10, \"sumName\": \"Vınø\", \"champLevel\": 17, \"goldEarned\": 14029, \"playerTeamID\": 
100}, {\"Champ\": \"Lillia\", \"kills\": 16, \"deaths\": 6, \"assists\": 9, \"sumName\": \"Master Eyla\", \"champLevel\": 17, \"goldEarned\": 16903, \"playerTeamID\": 100}, {\"Champ\": \"Ekko\", \"kills\": 13, \"deaths\": 4, \"assists\": 13, \"sumName\": \"Chaddam\", \"champLevel\": 17, \"goldEarned\": 16683, \"playerTeamID\": 100}, {\"Champ\": \"Lucian\", \"kills\": 7, \"deaths\": 13, \"assists\": 13, \"sumName\": \"Ahad\", \"champLevel\": 14, \"goldEarned\": 11527, \"playerTeamID\": 100}, {\"Champ\": \"Nami\", \"kills\": 2, \"deaths\": 6, \"assists\": 30, \"sumName\": \"White and 
Beasty\", \"champLevel\": 15, \"goldEarned\": 10131, \"playerTeamID\": 100}, {\"Champ\": \"Camille\", \"kills\": 16, \"deaths\": 8, \"assists\": 4, \"sumName\": \"Mazee\", \"champLevel\": 16, \"goldEarned\": 14656, \"playerTeamID\": 200}, {\"Champ\": \"Nocturne\", \"kills\": 3, \"deaths\": 8, \"assists\": 11, \"sumName\": \"aøtism\", \"champLevel\": 14, \"goldEarned\": 10260, \"playerTeamID\": 200}, {\"Champ\": \"Diana\", \"kills\": 5, 
\"deaths\": 10, \"assists\": 7, \"sumName\": \"aerichu\", \"champLevel\": 14, \"goldEarned\": 10636, \"playerTeamID\": 200}, {\"Champ\": \"Caitlyn\", \"kills\": 11, \"deaths\": 12, \"assists\": 11, \"sumName\": \"tempjppnyliavqxi\", \"champLevel\": 14, \"goldEarned\": 14868, \"playerTeamID\": 200}, {\"Champ\": \"Nautilus\", \"kills\": 2, \"deaths\": 13, \"assists\": 17, \"sumName\": \"SICKCXNT\", \"champLevel\": 13, \"goldEarned\": 8232, \"playerTeamID\": 200}]"
    },
    {
        "gameID":"NA1_4861910615",
        "gameVer":"13.24.547.9214",
        "gameDurationMinutes":"23:29",
        "gameCreationTimestamp":"1702748085427",
        "gameEndTimestamp":"1702749521862",
        "participants":"[\"kTcYIsJyAH2M5TvY8jyTp5AYQ4ODmwbP6kGZcXl18dhCagF0omsA2C5JJ2deILDMzxpfvYCwLDSgxQ\", \"XiOglNR7MR9h2R4WxW91KE1NRuZExZlokAZsC89OC1nNLK7Kr4bGBj9HR09lav5hnFWvS7IOWETUQA\", \"K98iyuDBR8uxwPa9oV82iOXP4DQFwtbL7Wu4fOlk_mpK3HpAxr7af_-aykzxP8OFN9B6gbdQDEW11g\", \"5_YZLTKs2t4EhkHdULJMFiVR9-_42ZC91AXCLBGhyR4f6oLTXJGbrNNmxwsDZsuTXkvOshaNBpVBTg\", \"JIQLaRJ68Hl6rSxqyePOZIQT20_xwBmSplkOie4BQpJKGcbHBpEHoiD_jF7NgdITT4-b9cxhVjBQCg\", \"Y7yObH4j-2NqohYahcjg94Nhdr50Mte1m2w9LEgDhLzTvcqcV9p5wc4eL9eqwXJZIpAvsLDvQzBgSQ\", \"kQq-q522qls652WMNaz07PdVOYQh0uQw-Exc6THzqMa06J86iE3vlgCQpvuCN5I6kxoIzWEQkqmmOw\", \"ciGjjxTNukVydeOUgADBWTFpr8rKjdZCV4LUu5-ta7Qi7BqyIMeaOxoBtO1FDuI9ZJWwDwc13R8QKQ\", \"iZjCQakO_GQHD2wtMwq0FWzWJBXXwo02YM2Q-31mXni7R9hY-mneMO_-ha47C2gazYKf28kw9iBVpQ\", \"yE9lBwxhABVgpvZeN5uk5-1zirNDfCGCE8tiiVQAJ1jsxKPDBGL7FgeOAWbEJu5O5MKCqrOIsCH8cQ\"]",
        "matchdata":"[{\"Champ\": \"Sona\", \"kills\": 2, \"deaths\": 5, \"assists\": 11, \"sumName\": \"Kennies\", \"champLevel\": 11, \"goldEarned\": 6956, \"playerTeamID\": 100}, {\"Champ\": \"Khazix\", \"kills\": 11, \"deaths\": 3, \"assists\": 7, \"sumName\": \"Leroy IV\", \"champLevel\": 15, \"goldEarned\": 12438, \"playerTeamID\": 100}, {\"Champ\": \"Ekko\", \"kills\": 2, \"deaths\": 3, \"assists\": 4, \"sumName\": \"Chaddam\", \"champLevel\": 15, \"goldEarned\": 9377, \"playerTeamID\": 100}, {\"Champ\": \"Ashe\", \"kills\": 4, \"deaths\": 3, \"assists\": 6, \"sumName\": \"Tradition\", \"champLevel\": 11, \"goldEarned\": 8308, \"playerTeamID\": 100}, {\"Champ\": \"Tryndamere\", \"kills\": 17, \"deaths\": 1, \"assists\": 
6, \"sumName\": \"Turkosaurus\", \"champLevel\": 17, \"goldEarned\": 16232, \"playerTeamID\": 100}, {\"Champ\": \"Urgot\", \"kills\": 1, \"deaths\": 12, \"assists\": 1, \"sumName\": \"lrobins\", \"champLevel\": 13, \"goldEarned\": 7343, \"playerTeamID\": 200}, {\"Champ\": \"XinZhao\", \"kills\": 1, \"deaths\": 7, \"assists\": 8, \"sumName\": \"IVIyth\", \"champLevel\": 12, \"goldEarned\": 7845, \"playerTeamID\": 200}, {\"Champ\": \"Lissandra\", \"kills\": 3, \"deaths\": 6, \"assists\": 0, \"sumName\": \"ImaKitcat\", \"champLevel\": 13, \"goldEarned\": 7930, \"playerTeamID\": 200}, {\"Champ\": \"Twitch\", \"kills\": 5, \"deaths\": 7, \"assists\": 7, \"sumName\": \"0NLYBLUE\", \"champLevel\": 12, \"goldEarned\": 9498, \"playerTeamID\": 200}, {\"Champ\": \"Karma\", \"kills\": 5, \"deaths\": 4, \"assists\": 6, \"sumName\": \"CLG DoubIelift\", \"champLevel\": 11, \"goldEarned\": 7927, \"playerTeamID\": 200}]"
    },
    {
        "gameID":"NA1_4846113883",
        "gameVer":"13.23.544.5515",
        "gameDurationMinutes":"26:20",
        "gameCreationTimestamp":"1701406452044",
        "gameEndTimestamp":"1701408100734",
        "participants":"[\"3t7fxfM2e8cwYC4P7hjt-PZMI6EbMUyeRXnWMzKLC7LN4Eci-QqVqJQ9rP1mCZw0MOSzGUPE1_xm1g\", \"U8dF6IA8h77KCCYHahsljEm6HGvXh3QlsMwppGG4BiyfCW9SoGjdl6zjVtsFGXdxvOstoqiR0wJALQ\", 
\"t1bifvwWWmFeYUiNZ2RBYXKn1jRzYUOl2EtnRo-GeSTiBTAUAkvu_DCjDwoFzWfRhI7ZSm1k1AhA6Q\", \"wAlfNckJRU2bK5Yi4ZkiadzPCLEA_Y3NhEniQMmvbB9Ho-H9CRJLIZ5aH9jBUXHGVwji9MK6_bt-nA\", \"Ve4eJ_1X4egHxi9bh7DJxrJuCFonNNOhb-iEDRrguKwAAk_TnjfeNla7ayVam_4mqrPp0mEVmbhoSg\", \"7TEDNkg5uJt4ZiBJ17TAQ98M5hEblFxIJEleRIb1Yl68NoBWBzC7Axvu2-f3-u5YTlQm4H-r6w7Y4w\", \"K98iyuDBR8uxwPa9oV82iOXP4DQFwtbL7Wu4fOlk_mpK3HpAxr7af_-aykzxP8OFN9B6gbdQDEW11g\", \"rM4l181-_BnLSnaFrIluFuyuKZBmvRvDqQbsmYP_w2Tqcyez9Ftxf57YiAORDe5u55K_lkJOVezjvQ\", \"3hJ3TkQAUn6xrPPbHvjBxJOO-8W_MbQRUA6G5oGdh9Ge-zuli2GseWiKWEWRoxH9tNLVsPrrsid24g\", \"HwYNmyPU3OPCXJ2tEYgBoPsCxOjRu2RfKDUClzhe0Re4DVBkyrOQuP0w2wY_ksuSiNl8b5sw7eB7bQ\"]",
        "matchdata":"[{\"Champ\": \"Yone\", \"kills\": 4, \"deaths\": 8, \"assists\": 4, \"sumName\": \"jcsys\", \"champLevel\": 15, \"goldEarned\": 10853, \"playerTeamID\": 100}, {\"Champ\": \"Briar\", \"kills\": 11, \"deaths\": 15, \"assists\": 10, \"sumName\": \"KR sexKing\", \"champLevel\": 13, \"goldEarned\": 12052, \"playerTeamID\": 100}, {\"Champ\": \"Veigar\", \"kills\": 7, \"deaths\": 7, \"assists\": 7, \"sumName\": \"Outkai\", \"champLevel\": 13, \"goldEarned\": 9877, \"playerTeamID\": 100}, {\"Champ\": \"Ezreal\", \"kills\": 11, \"deaths\": 7, \"assists\": 5, \"sumName\": \"dmf2810\", \"champLevel\": 12, \"goldEarned\": 12222, \"playerTeamID\": 100}, {\"Champ\": \"Senna\", \"kills\": 1, \"deaths\": 8, \"assists\": 17, \"sumName\": \"WonderPanda\", \"champLevel\": 11, \"goldEarned\": 8080, \"playerTeamID\": 100}, {\"Champ\": \"Illaoi\", \"kills\": 4, \"deaths\": 6, \"assists\": 5, \"sumName\": \"Kampsycho\", \"champLevel\": 16, \"goldEarned\": 11266, \"playerTeamID\": 200}, {\"Champ\": \"Ekko\", 
\"kills\": 5, \"deaths\": 9, \"assists\": 8, \"sumName\": \"Chaddam\", \"champLevel\": 15, \"goldEarned\": 11474, \"playerTeamID\": 200}, {\"Champ\": \"Vex\", \"kills\": 9, \"deaths\": 5, \"assists\": 10, \"sumName\": \"Toctex\", \"champLevel\": 16, \"goldEarned\": 14216, \"playerTeamID\": 200}, {\"Champ\": \"Draven\", \"kills\": 14, \"deaths\": 8, \"assists\": 6, \"sumName\": \"mJiang\", \"champLevel\": 15, \"goldEarned\": 16898, \"playerTeamID\": 200}, {\"Champ\": \"Sylas\", \"kills\": 13, \"deaths\": 6, \"assists\": 13, \"sumName\": \"An Icon\", \"champLevel\": 13, \"goldEarned\": 12025, \"playerTeamID\": 200}]"
    },
    {
        "gameID":"NA1_4846075216",
        "gameVer":"13.23.544.5515",
        "gameDurationMinutes":"26:49",
        "gameCreationTimestamp":"1701404479202",
        "gameEndTimestamp":"1701406111606",
        "participants":"[\"Rhc2cjaaz87AQfxqFA6ZF5loZVdb6i0LW3ycGR4yFEdrdP_BL0hEN4QOMaH1_9lFLrtmMhsQ2RV2wQ\", \"K98iyuDBR8uxwPa9oV82iOXP4DQFwtbL7Wu4fOlk_mpK3HpAxr7af_-aykzxP8OFN9B6gbdQDEW11g\", \"0vzdXwz6znNNCWXsb6a_-X4m6gnIHO0fszr_rWpGmDM04aESepLVRY8UarjZCqBf7dM-MSFdlr_yUw\", \"XB0qUDQA_vriZ-8N-4Ft8gVYBMrYrenE0_23FXgWQT1CSaZhTNv3cVH9_urFn08a8UhkubB6vxr_Jg\", \"wL9dpL_fRhtAjE_zFEYggLjuBBbqhA3TGgP0BgsqpvMuf0UCMena_6vnnjMcYKKKHyoEHs6m1IZY1A\", \"PlRjJPOZQuVv4Sm01DjMy6x79HjnN9pJkywfN3KzDElbv2nkveot2eNn6PhMSzMEGcOtyuf5OH2ATw\", \"VSgR4cKZLFkR_sbeylj5VllYSqSiuXkcZtXZvZeH-oxori273Pz6ATpFyos0Ed8J67o-JKf6fvocuA\", \"l2mwRsoC2GBefgg4HVyyzyKZi34nqvAlde3cvmzrbV6g6IFopBtGq0NqsUlSeGAXpvB6j__HOokc8Q\", \"Vhy4aUo6lHBTFEbLQi8KHlAIXMGKkJhBIXQznLugSiq6uIjviqqOuZ93Z1v6ykG0AT0D48bYUd7OdA\", \"lA795NTDusgv77vzhh2RaE4p34DUePPsNsQHXHbpgYsy5N-FINj0hevro1PrM-Lr5iXF45z_EIgY-g\"]",
        "matchdata":"[{\"Champ\": \"Rumble\", \"kills\": 5, \"deaths\": 7, \"assists\": 0, \"sumName\": \"Highflame\", \"champLevel\": 15, \"goldEarned\": 9350, \"playerTeamID\": 100}, {\"Champ\": \"Shaco\", \"kills\": 6, \"deaths\": 4, \"assists\": 4, \"sumName\": \"Chaddam\", \"champLevel\": 14, \"goldEarned\": 9938, \"playerTeamID\": 100}, {\"Champ\": \"Yone\", \"kills\": 4, \"deaths\": 7, \"assists\": 3, \"sumName\": \"Thrithet\", \"champLevel\": 14, \"goldEarned\": 9171, \"playerTeamID\": 100}, {\"Champ\": \"Caitlyn\", \"kills\": 2, \"deaths\": 6, \"assists\": 5, \"sumName\": \"Boy Long Xuyên\", \"champLevel\": 13, \"goldEarned\": 9702, \"playerTeamID\": 100}, {\"Champ\": \"Leona\", \"kills\": 2, \"deaths\": 3, \"assists\": 6, \"sumName\": \"pommegrenade\", \"champLevel\": 12, \"goldEarned\": 6053, \"playerTeamID\": 100}, {\"Champ\": \"Fiora\", \"kills\": 2, \"deaths\": 5, \"assists\": 4, \"sumName\": \"Umbrell4\", \"champLevel\": 15, \"goldEarned\": 11094, \"playerTeamID\": 200}, {\"Champ\": \"Talon\", 
\"kills\": 14, \"deaths\": 0, \"assists\": 2, \"sumName\": \"IlIlIllIlIIII\", \"champLevel\": 17, \"goldEarned\": 15150, \"playerTeamID\": 200}, 
{\"Champ\": \"Azir\", \"kills\": 2, \"deaths\": 6, \"assists\": 5, \"sumName\": \"Stardustpug\", \"champLevel\": 16, \"goldEarned\": 10910, \"playerTeamID\": 200}, {\"Champ\": \"MissFortune\", \"kills\": 7, \"deaths\": 4, \"assists\": 3, \"sumName\": \"Eburibat\", \"champLevel\": 14, \"goldEarned\": 13992, \"playerTeamID\": 200}, {\"Champ\": \"Thresh\", \"kills\": 2, \"deaths\": 4, \"assists\": 10, \"sumName\": \"Angelofwhat\", \"champLevel\": 13, \"goldEarned\": 8491, \"playerTeamID\": 200}]"
    },
    {
        "gameID":"NA1_4843993298",
        "gameVer":"13.23.544.5515",
        "gameDurationMinutes":"26:07",
        "gameCreationTimestamp":"1701214730107",
        "gameEndTimestamp":"1701216315501",
        "participants":"[\"kvd6XmvyGl2sox0W0wInU8nbRFLwapALbtDxCIZPzS_eVjAHVIqt0XJ86RRv_UFwmemqIG5LSuhpXg\", \"FLekcExVzUEVzmTB3N6_5UOBJfhXe3JS0E0Til1LBFDvREGBjOOnvjXTYqG_GUJjoJEDUjv_Autkvw\", \"tne7C9-n9Une2ftyM7-7Ucc2LdsetDQPxgDmIP19dp2Ky6DEZIVPxKDKwNGvkl9eyPNjC3tbyPu5pQ\", \"p_pmC-lpqEpl1UGXrgLuU_2-7Ir6wN7U2nDZ3OoW4zKS4OPPc_T_zX7QFwc46TUddjdEU06s9i3qmg\", \"rWHLKjZz8lG8mF3ynbT9tJvXByQQDbHCuqKZc93oJyM5e7urf6Bzj7SjioBtSak6NdA8D7CQHMHAMQ\", \"auPCedXF9PQds2oaw7y7JZbh_cJHQ23K0v0rSi5IETDsiVeobUP4h4_N1ewsR34xs5d58syfgznBTg\", \"K98iyuDBR8uxwPa9oV82iOXP4DQFwtbL7Wu4fOlk_mpK3HpAxr7af_-aykzxP8OFN9B6gbdQDEW11g\", \"5yGZPib-hMudz02NKSIYC07uK6N9ulltZaEhX-kzShx9_HYpO-nOAt_mA2Zg0-s7pR0e3g18r9s2Kg\", \"B1Y31ueQjrc6euroDnAprAwtK-5HW3ASO1_-uH46sg8uMvCr4SvdVWR3MLPwERNkbDQn-M2Y8JSvDQ\", \"x91iIvNhAatWpiwvQQviFAUA0lD6uI8lrp2UiMXmUdYJJc_k43cABaj9Ko2hEbpmPYORyDL72g2WVg\"]",
        "matchdata":"[{\"Champ\": \"Cassiopeia\", \"kills\": 4, \"deaths\": 7, \"assists\": 5, \"sumName\": \"Snektop\", \"champLevel\": 16, \"goldEarned\": 9757, \"playerTeamID\": 100}, {\"Champ\": \"RekSai\", \"kills\": 6, \"deaths\": 3, \"assists\": 6, \"sumName\": \"AKA Mr Black\", \"champLevel\": 14, \"goldEarned\": 10597, \"playerTeamID\": 100}, {\"Champ\": \"Zoe\", \"kills\": 7, \"deaths\": 0, \"assists\": 5, \"sumName\": \"Getö Suguru\", \"champLevel\": 16, \"goldEarned\": 12875, \"playerTeamID\": 100}, {\"Champ\": \"Caitlyn\", \"kills\": 12, \"deaths\": 4, \"assists\": 10, \"sumName\": \"MLG Rhyder Nocap\", \"champLevel\": 16, \"goldEarned\": 16818, \"playerTeamID\": 100}, {\"Champ\": 
\"Pyke\", \"kills\": 8, \"deaths\": 4, \"assists\": 7, \"sumName\": \"MLG 1shot5kills\", \"champLevel\": 14, \"goldEarned\": 9564, \"playerTeamID\": 100}, {\"Champ\": \"Akali\", \"kills\": 8, \"deaths\": 9, \"assists\": 2, \"sumName\": \"Limitless IV\", \"champLevel\": 14, \"goldEarned\": 10107, \"playerTeamID\": 200}, {\"Champ\": \"Shaco\", \"kills\": 3, \"deaths\": 8, \"assists\": 4, \"sumName\": \"Chaddam\", \"champLevel\": 13, \"goldEarned\": 8985, \"playerTeamID\": 200}, {\"Champ\": \"Orianna\", \"kills\": 2, \"deaths\": 5, \"assists\": 3, \"sumName\": \"RupDog\", \"champLevel\": 14, \"goldEarned\": 7747, \"playerTeamID\": 200}, {\"Champ\": \"MissFortune\", \"kills\": 5, \"deaths\": 6, \"assists\": 2, \"sumName\": \"Expedited\", \"champLevel\": 14, \"goldEarned\": 11539, \"playerTeamID\": 200}, {\"Champ\": \"Leona\", \"kills\": 0, \"deaths\": 9, \"assists\": 7, \"sumName\": \"Banhmi Boi\", \"champLevel\": 11, \"goldEarned\": 5531, \"playerTeamID\": 200}]"
    },
    {
        "gameID":"NA1_4843960380",
        "gameVer":"13.23.544.5515",
        "gameDurationMinutes":"31:39",
        "gameCreationTimestamp":"1701212272322",
        "gameEndTimestamp":"1701214193831",
        "participants":"[\"ntZFBTQezrkYd-09Xj0IRB2q35Fvhzk6ymOWwRvb2Hj4sdBJbJHq4QTXHpiJthaXmQbYGChlCVs6cw\", \"K98iyuDBR8uxwPa9oV82iOXP4DQFwtbL7Wu4fOlk_mpK3HpAxr7af_-aykzxP8OFN9B6gbdQDEW11g\", \"-LBBF4JxVMuAszT2qify2ZLl9zZzkaLoKD6kw8yR6XeeBrWRsl4FkRGhIcVXTMwjlmxep6B8OC8Opw\", \"0JC0FMu6Pzx4fPPxisFNbAvA93FgB_nHyjv6mPx2xLU_jDb_F0KbjWL5qmE4rNnc0zLGBZXQrfJhDQ\", \"UQFqg3JNpap5ULTXREMwiqpkHGVEOVCZ36600g8THBVmDAe_UwC7SxKRcscvfXH3kpeBB4ajvLZFoA\", \"k0tH-GdG0lzl1WWzLq6uT1LO2W8MH35ZsYDLwToSGQihLVDQ_HtvFoIdBc-5_ZP8FRFOYuseMII4dw\", \"2cyhrUjibPGwDjVsNWyNRYmbvhK8GxdPyNN8GRCurF-KcUNgNz3CIAAZ1VZoNQvE9xRl7blTSL_GNg\", \"PPUmLZel7TkeP7uKjVZ3zdwNE5eRFqZRwnYERTkwYQIx49YQKO4OSUfCr1ilPO5-vIvfDYO-QseRuA\", \"hZhMqg7r57pt8EnMvfzhEiCGLo9vSJYOHeBVcV1Qpkzd2r-yM35UXh2PNT5rggbaty97v5wozwOx5Q\", \"JmX3pSTbx2LNBtLCQMjtoSGfqtMRX5KzwLirWdAkUrmdeaEnxvMBZRvGICh3BgPXJo8ty1GCiHHH-g\"]",
        "matchdata":"[{\"Champ\": \"Chogath\", \"kills\": 8, \"deaths\": 2, \"assists\": 4, \"sumName\": \"MrMartian\", \"champLevel\": 18, \"goldEarned\": 14515, \"playerTeamID\": 100}, {\"Champ\": \"Shaco\", \"kills\": 7, \"deaths\": 5, \"assists\": 9, \"sumName\": \"Chaddam\", \"champLevel\": 16, \"goldEarned\": 13173, \"playerTeamID\": 100}, {\"Champ\": \"Fizz\", \"kills\": 11, \"deaths\": 6, \"assists\": 7, \"sumName\": \"Røoz\", \"champLevel\": 17, \"goldEarned\": 14299, \"playerTeamID\": 100}, {\"Champ\": \"Caitlyn\", \"kills\": 9, \"deaths\": 2, \"assists\": 8, \"sumName\": \"ImDecent\", \"champLevel\": 15, \"goldEarned\": 13639, \"playerTeamID\": 100}, 
{\"Champ\": \"Senna\", \"kills\": 1, \"deaths\": 5, \"assists\": 19, \"sumName\": \"advocate\", \"champLevel\": 15, \"goldEarned\": 10419, \"playerTeamID\": 100}, {\"Champ\": \"Fiora\", \"kills\": 1, \"deaths\": 7, \"assists\": 1, \"sumName\": \"Pigeonman8\", \"champLevel\": 16, \"goldEarned\": 
11728, \"playerTeamID\": 200}, {\"Champ\": \"Graves\", \"kills\": 4, \"deaths\": 7, \"assists\": 10, \"sumName\": \"inkyxyz\", \"champLevel\": 16, 
\"goldEarned\": 13522, \"playerTeamID\": 200}, {\"Champ\": \"Tristana\", \"kills\": 9, \"deaths\": 4, \"assists\": 2, \"sumName\": \"yeahhh ok\", \"champLevel\": 16, \"goldEarned\": 15075, \"playerTeamID\": 200}, {\"Champ\": \"Karthus\", \"kills\": 4, \"deaths\": 11, \"assists\": 7, \"sumName\": \"D1fferent\", \"champLevel\": 15, \"goldEarned\": 11455, \"playerTeamID\": 200}, {\"Champ\": \"Ashe\", \"kills\": 2, \"deaths\": 7, \"assists\": 8, \"sumName\": \"killzoneAK47\", \"champLevel\": 12, \"goldEarned\": 8008, \"playerTeamID\": 200}]"
    },
    {
        "gameID":"NA1_4843353612",
        "gameVer":"13.23.544.5515",
        "gameDurationMinutes":"29:41",
        "gameCreationTimestamp":"1701143293013",
        "gameEndTimestamp":"1701145101070",
        "participants":"[\"wM4h34NOtIUOEyugP1j3BtxUncnYIb_pqh9JoRh95ZpE5MnbScczBG9doPho6poWiRuh7auAWf0Vhw\", \"5D_fIpB6N_w_MIYRADy_87JjqK7bY4VpuIQNl2DLUUVk_UcDuIFShzj7eHFnVXWvoAugSC8k28u7YA\", \"HHYL2ZspsMpUH9TDze_uqQdb8hmad4rZf6JGn0Nx6TQp6GHGHZQzpide4oH6NpE6APD8aEwDhQIY5A\", \"OXhVOSe7eifUiYfsod_PeJSA9hkZXlEgIEA4F5rw9DTGXajs0qCdzCtYPQW7PFyXu64WloNxV1U6dA\", \"AE_cokW6umIOomKOoiH95FPlbFfRCYgMZUFo0YSko34vQ60sBtyndxJhY0Y29QKoK9zWtB8KFFtY2Q\", \"1u6EW46AFC-zDMz_l-JwvkZtRfJEvuKD6uI2hoyI6qzEZ6aPhQ-MK9AhhPvqu8iPB1MGvb-jEiBvhw\", 
\"K98iyuDBR8uxwPa9oV82iOXP4DQFwtbL7Wu4fOlk_mpK3HpAxr7af_-aykzxP8OFN9B6gbdQDEW11g\", \"TD3L8odGACFjUbcEXxneC-iTh3OkB91VNoZ5ThTLh6YnVen3AASo0c6swb6Gn6XTnOhnCS0xriNXww\", \"S3L1TZv6KTZVeYmXWCUDYqv5g0JT8BEk-KZR8Zr9QNXsvKwjf-NHNXy8At0JLZ_RLqdCGkbRK5F5HQ\", \"i5aHcO60VZ2cv6s16XiNmcHMq9aC5NjlNrdvShqt4BTAjAjglcTX_AsgaVyvk20qFKT3gXaU4pcJuA\"]",
        "matchdata":"[{\"Champ\": \"MonkeyKing\", \"kills\": 4, \"deaths\": 8, \"assists\": 7, \"sumName\": \"Rices\", \"champLevel\": 15, \"goldEarned\": 11408, \"playerTeamID\": 100}, {\"Champ\": \"Ivern\", \"kills\": 3, \"deaths\": 2, \"assists\": 13, \"sumName\": \"Unami\", \"champLevel\": 14, \"goldEarned\": 10236, \"playerTeamID\": 100}, {\"Champ\": \"Kassadin\", \"kills\": 7, \"deaths\": 8, \"assists\": 4, \"sumName\": \"kükü naber ya\", \"champLevel\": 13, \"goldEarned\": 10292, \"playerTeamID\": 100}, {\"Champ\": \"Caitlyn\", \"kills\": 9, \"deaths\": 7, \"assists\": 5, \"sumName\": \"PizzaThatAshe\", \"champLevel\": 16, \"goldEarned\": 15173, \"playerTeamID\": 100}, {\"Champ\": \"Lux\", \"kills\": 6, \"deaths\": 6, \"assists\": 5, \"sumName\": \"Grogu Fan Boy\", \"champLevel\": 12, \"goldEarned\": 8923, \"playerTeamID\": 100}, {\"Champ\": \"Illaoi\", \"kills\": 6, \"deaths\": 7, \"assists\": 2, \"sumName\": \"JKwhy\", \"champLevel\": 16, \"goldEarned\": 13076, \"playerTeamID\": 200}, {\"Champ\": \"Shaco\", \"kills\": 6, \"deaths\": 3, \"assists\": 5, \"sumName\": \"Chaddam\", \"champLevel\": 16, \"goldEarned\": 12990, \"playerTeamID\": 200}, {\"Champ\": \"Sylas\", \"kills\": 7, \"deaths\": 6, \"assists\": 7, \"sumName\": \"Dravise123\", \"champLevel\": 16, \"goldEarned\": 12861, \"playerTeamID\": 200}, {\"Champ\": \"Jhin\", \"kills\": 8, \"deaths\": 4, \"assists\": 4, \"sumName\": \"JAN1337\", \"champLevel\": 15, \"goldEarned\": 12802, \"playerTeamID\": 200}, {\"Champ\": \"Zyra\", \"kills\": 4, \"deaths\": 
9, \"assists\": 12, \"sumName\": \"Alasdair Mcrazy\", \"champLevel\": 14, \"goldEarned\": 10096, \"playerTeamID\": 200}]"
    },
    {
        "gameID":"NA1_4831134162",
        "gameVer":"13.22.541.9804",
        "gameDurationMinutes":"38:48",
        "gameCreationTimestamp":"1700094392173",
        "gameEndTimestamp":"1700096740198",
        "participants":"[\"BwM8fbuGZOG3XrgONnopGg_frg20eCmhgxwvW9FnyoDzLaC4xjGCtoAzEeoWmHL7EfLlxgweq1VNFQ\", \"NttcikPctxbDvKPG8ebjUDXImhnVTf41VqOCtqxEVGu3SadxEodf7WtVJZTQZ_UW97YNAZiJVXD1GQ\", \"Um4crd9QR-wSogfqrYSnsj-P8bOpNbaPHsvuE4s7nKWkeRb4S9uc0uH_eobNwW2_wzUqVHYVfh0oRg\", \"S3Erd4Ef4IL9tel9VytRzgufRhDJjBWdCokB4IaQcPJoO70pVljILIEd4BEKzSdCqsr38UZp08phtg\", \"HJHVccbhpf2ADhKooPEXJFH0MZVE44navV5wrA_z_tLvix96smYH9xQk1rDaqF-ul67lSkGUJRoCqg\", \"u0ziQ0VC6VFq6XAoesfm4QROJyO8A_PXr-rZMRct8W3owNszKvkXXR0jhXW4yJX8RbyN-yza5hs5gg\", \"K98iyuDBR8uxwPa9oV82iOXP4DQFwtbL7Wu4fOlk_mpK3HpAxr7af_-aykzxP8OFN9B6gbdQDEW11g\", \"_STg9Gkltq9GLLHy4FgHwDqxtTTCNkwtuL1V7yk3wyduKCFPsRWCcmvI2z_05-DFLVYsfBAIGneIQQ\", \"DYzUwG5wAzOH85SY7VeGlZwv6VQf1bn34RwDpKFVb8a3BntwrXgJBXZ-nRHLejfSmEqiOUlm8hEWTw\", \"dex2vpfvR1VEsh-K1i2uFI6yzStljnBxbIwbCMPZf7LbwEvZVjTB5VncpEBFZUM7_LpH6oGCG28ZkQ\"]",
        "matchdata":"[{\"Champ\": \"Gragas\", \"kills\": 15, \"deaths\": 2, \"assists\": 4, \"sumName\": \"giv3 me lp\", \"champLevel\": 18, \"goldEarned\": 21177, \"playerTeamID\": 100}, {\"Champ\": \"JarvanIV\", \"kills\": 4, \"deaths\": 8, \"assists\": 11, \"sumName\": \"CloudStack\", \"champLevel\": 16, \"goldEarned\": 13373, \"playerTeamID\": 100}, {\"Champ\": \"Pantheon\", \"kills\": 8, \"deaths\": 12, \"assists\": 6, \"sumName\": \"iiSly\", \"champLevel\": 17, \"goldEarned\": 14332, \"playerTeamID\": 100}, {\"Champ\": \"Twitch\", \"kills\": 11, \"deaths\": 4, \"assists\": 11, \"sumName\": \"RATEATER27\", \"champLevel\": 18, 
\"goldEarned\": 17784, \"playerTeamID\": 100}, {\"Champ\": \"Yuumi\", \"kills\": 3, \"deaths\": 2, \"assists\": 21, \"sumName\": \"Qwerky\", \"champLevel\": 17, \"goldEarned\": 10327, \"playerTeamID\": 100}, {\"Champ\": \"Gwen\", \"kills\": 8, \"deaths\": 9, \"assists\": 4, \"sumName\": \"Yung 
Deedle\", \"champLevel\": 18, \"goldEarned\": 17584, \"playerTeamID\": 200}, {\"Champ\": \"Shaco\", \"kills\": 7, \"deaths\": 3, \"assists\": 10, 
\"sumName\": \"Chaddam\", \"champLevel\": 18, \"goldEarned\": 15966, \"playerTeamID\": 200}, {\"Champ\": \"Naafiri\", \"kills\": 8, \"deaths\": 6, 
\"assists\": 8, \"sumName\": \"Dog Hentai\", \"champLevel\": 18, \"goldEarned\": 15347, \"playerTeamID\": 200}, {\"Champ\": \"Nilah\", \"kills\": 2, \"deaths\": 14, \"assists\": 7, \"sumName\": \"Jhym\", \"champLevel\": 18, \"goldEarned\": 15849, \"playerTeamID\": 200}, {\"Champ\": \"Pyke\", \"kills\": 3, \"deaths\": 9, \"assists\": 11, \"sumName\": \"surely no\", \"champLevel\": 14, \"goldEarned\": 10639, \"playerTeamID\": 200}]"
    },
    {
        "gameID":"NA1_4831098965",
        "gameVer":"13.22.541.9804",
        "gameDurationMinutes":"37:53",
        "gameCreationTimestamp":"1700091662281",
        "gameEndTimestamp":"1700094014191",
        "participants":"[\"s4TVnIvlNLCTEZKF4NbrylSPhs_OvNnb4ZQo6HfZPtiYjeAZMxmhJPo4duudMeKlSbfCSbj8BtGwfw\", \"-ojJw85edyuH1tdQglH0iYJC_gjsUriuh600ybJR3tfTKPCF3GledrZm89a0guoVgOmp35Z6wNYH2A\", \"edmeanNT1NYqqZCmDLamh2SYWtmGdR-IitHa8-siXwm0OWTP7kNlbYT1347lo_k68_XRt-nSWGEYsQ\", \"Mfbigd6NZLnbtRsvvW7yIDzRvyoXKq9wImb64fbJwBuC70Xkgf8sh5j_oJk0HPS6822lxaKtkgvuEw\", \"rOMLFPPXU39gg6Aznj0-cztuAmY1ikDehxzAcM0GTn68JFc2GMZSQZmvm_xv1KV7iEnc-wTxF8NxkA\", \"k9qqNf3ekLJu6x6O-BGNhh1-koK_j58UW6a9ruvGqY62PyZ8XSTzWwREH8F86tdgZv0HFzmX1mYgZQ\", \"dmRO4lz2RbstAeIFOxzvX_Qce-LvEDD-gvWF6SIJrVm2aK8myT8o_Bcs3l4_rWaKCP5aXETVR3JcLw\", \"K98iyuDBR8uxwPa9oV82iOXP4DQFwtbL7Wu4fOlk_mpK3HpAxr7af_-aykzxP8OFN9B6gbdQDEW11g\", \"VvsNRTxGodPOtrBjY-rULs5lde5mMIVCNqDHxgdXTChd3XPC8ZMBCCIrcRMNSig5udGBVrlfTCkE-A\", \"X0YODzPFuNu61Dv4vQXJp29FUUs-FOj3IEAVl7HhIrCDBpZwHF8ndj6j0a5Rh7QEW1PAf7uDC8n1lQ\"]",
        "matchdata":"[{\"Champ\": 
\"Yone\", \"kills\": 9, \"deaths\": 6, \"assists\": 8, \"sumName\": \"yoyokiller\", \"champLevel\": 18, \"goldEarned\": 20539, \"playerTeamID\": 100}, {\"Champ\": \"Evelynn\", \"kills\": 18, \"deaths\": 4, \"assists\": 11, \"sumName\": \"Posture Facture\", \"champLevel\": 18, \"goldEarned\": 18447, \"playerTeamID\": 100}, {\"Champ\": \"Veigar\", \"kills\": 3, \"deaths\": 9, \"assists\": 10, \"sumName\": \"RunnyFartSIave42\", \"champLevel\": 17, \"goldEarned\": 13753, \"playerTeamID\": 100}, {\"Champ\": \"MissFortune\", \"kills\": 8, \"deaths\": 7, \"assists\": 6, \"sumName\": \"Fxxknxxbs2021\", \"champLevel\": 16, \"goldEarned\": 15717, \"playerTeamID\": 100}, {\"Champ\": \"Thresh\", \"kills\": 0, \"deaths\": 12, \"assists\": 14, \"sumName\": \"eywnc\", \"champLevel\": 15, \"goldEarned\": 9182, \"playerTeamID\": 100}, {\"Champ\": \"Gnar\", \"kills\": 3, \"deaths\": 11, \"assists\": 4, \"sumName\": \"Dem Poroz\", \"champLevel\": 17, \"goldEarned\": 12133, \"playerTeamID\": 200}, {\"Champ\": \"Viego\", \"kills\": 
7, \"deaths\": 11, \"assists\": 9, \"sumName\": \"ƒ Red Kayn ƒ\", \"champLevel\": 16, \"goldEarned\": 13185, \"playerTeamID\": 200}, {\"Champ\": 
\"Ekko\", \"kills\": 6, \"deaths\": 7, \"assists\": 5, \"sumName\": \"Chaddam\", \"champLevel\": 17, \"goldEarned\": 13879, \"playerTeamID\": 200}, {\"Champ\": \"Jhin\", \"kills\": 16, \"deaths\": 4, \"assists\": 7, \"sumName\": \"SiIchas Ruin\", \"champLevel\": 18, \"goldEarned\": 20100, \"playerTeamID\": 200}, {\"Champ\": \"Karma\", \"kills\": 3, \"deaths\": 5, \"assists\": 21, \"sumName\": \"dOinK WinS\", \"champLevel\": 17, \"goldEarned\": 11181, \"playerTeamID\": 200}]"
    },
    {
        "gameID":"NA1_4816328470",
        "gameVer":"13.21.539.4823",
        "gameDurationMinutes":"28:37",
        "gameCreationTimestamp":"1698723448925",
        "gameEndTimestamp":"1698725216745",
        "participants":"[\"oFreJeTwFEA3lyU7jR3CNaifCS0IsObpGfW2IrtVDc60yB29QXFtoS0sRwniG8sSH0EOzXpBwfxhXw\", \"PjlfbhtYz8nnpC8OOcfniCttfzLO_e04mbl7iAkeKSICECvHSsy3WosJdpJPVFh3ENxFX5v1n-VyXA\", \"K98iyuDBR8uxwPa9oV82iOXP4DQFwtbL7Wu4fOlk_mpK3HpAxr7af_-aykzxP8OFN9B6gbdQDEW11g\", \"Hbd5j3sfm1iT80qV5jA3BuQdmDLtigw8xieCm4-599WR9BoEDRnA48DK3mISKvOG4PleoudxMwtBQw\", \"whm1Nk7FJ39Cf2Uzt_1WUHn3yDJgXz-1UPR9pUPzHdfE6GDXJTR6JcTc1X4GV3CbxDOuyAxmCiIwTw\", \"0ebB4SWn49EVycs0TFe90bQPNc-412uRVZq1-13iCLRl2zqa5lBHYQyg0YDf6hXOsMOUwCi44ZDVZQ\", \"fO375vNS0i9HzL6qG5PSYyfxiTwinaPTNu2CWLCr3Zq7V8IJKkvhiEurtgZZS_tcHSry05gH8Vq8oQ\", \"S0j0Sr5G7TqEZYyHPffHkc7UygB3YRyK8VNWouZbk5YU58EcHtLsAFjz_FFdudRTqvN6v8RpKhYkgQ\", \"7FY5JDEx-ChEyZTFWFmrBAyqYsw_JZudOL__k6sB7WpG22VT7RYYKr6G_R0UnFmUk7jXfYykFARDsg\", \"rFeYJwGqsXpgNIMKCIHXzrrHmF52rC6LuqzeHNPoiExBW0bi2SGd869lDZ3dGYg3VPx9LbxdKyOYCw\"]",
        "matchdata":"[{\"Champ\": \"Illaoi\", \"kills\": 4, \"deaths\": 7, \"assists\": 5, \"sumName\": \"SuperStar683\", \"champLevel\": 
17, \"goldEarned\": 14293, \"playerTeamID\": 100}, {\"Champ\": \"Shaco\", \"kills\": 2, \"deaths\": 5, \"assists\": 9, \"sumName\": \"Smelly Shaco\", \"champLevel\": 14, \"goldEarned\": 10539, \"playerTeamID\": 100}, {\"Champ\": \"Ekko\", \"kills\": 4, \"deaths\": 2, \"assists\": 5, \"sumName\": \"Chaddam\", \"champLevel\": 16, \"goldEarned\": 11376, \"playerTeamID\": 100}, {\"Champ\": \"Ezreal\", \"kills\": 13, \"deaths\": 6, \"assists\": 5, \"sumName\": \"sha ß\", \"champLevel\": 16, \"goldEarned\": 14699, \"playerTeamID\": 100}, {\"Champ\": \"Zyra\", \"kills\": 8, \"deaths\": 7, \"assists\": 12, \"sumName\": \"WIhippiechick\", \"champLevel\": 12, \"goldEarned\": 11052, \"playerTeamID\": 100}, {\"Champ\": \"DrMundo\", \"kills\": 2, \"deaths\": 5, \"assists\": 5, \"sumName\": \"weew00weew00wee\", \"champLevel\": 15, \"goldEarned\": 9518, \"playerTeamID\": 200}, {\"Champ\": \"Briar\", \"kills\": 12, \"deaths\": 8, \"assists\": 5, \"sumName\": \"SovereignWarwick\", \"champLevel\": 13, \"goldEarned\": 12567, \"playerTeamID\": 200}, {\"Champ\": \"Orianna\", \"kills\": 3, \"deaths\": 3, \"assists\": 6, \"sumName\": \"Brook Hoodlum\", \"champLevel\": 15, \"goldEarned\": 10178, \"playerTeamID\": 200}, {\"Champ\": \"Xayah\", \"kills\": 10, \"deaths\": 6, \"assists\": 4, \"sumName\": \" Supp Stay By Me\", 
\"champLevel\": 15, \"goldEarned\": 13389, \"playerTeamID\": 200}, {\"Champ\": \"Thresh\", \"kills\": 0, \"deaths\": 10, \"assists\": 13, \"sumName\": \"Loriswen\", \"champLevel\": 12, \"goldEarned\": 6677, \"playerTeamID\": 200}]"
    },
    {
        "gameID":"NA1_4811150441",
        "gameVer":"13.21.537.9010",
        "gameDurationMinutes":"38:37",
        "gameCreationTimestamp":"1698280979749",
        "gameEndTimestamp":"1698283330112",
        "participants":"[\"LUSHN3otpVuj_TINPye9zSRoONcmy9CXBle9lYPWjQ12Y7Ok1E-gajSbWmDDCzySU-ZBXo1PVuTTwQ\", \"CJlfSH-8uEcwx9kkx4nMEnp8UcGGN_UjlwC7DF8zNeJbs0fSpkrCaKu8Wm7vFbMepXeN_c5VFy6hug\", \"K98iyuDBR8uxwPa9oV82iOXP4DQFwtbL7Wu4fOlk_mpK3HpAxr7af_-aykzxP8OFN9B6gbdQDEW11g\", \"Eb3kpHeksmgLcz-8XdoBIAkLvtSiGHLmyGmrrsGoBWtoaoQMlZAm6ptlK06qeRIlHKhz2D3vevXx9w\", \"9qHQt7u7PSEFLKMwYvEFVZ5yWzTtu_Ly3cq6Ui82MeFuF3mGBz-OR0L4anvpMDTrit5TfgArNB6K3A\", \"h8RT-s5ISgORAu_TkoN8qnbMzwMPtQaj22LQ6rhl2AEI-Pu_xkp_LtP2M8T-e6Gd9srT57CBbkA9Vw\", \"2kf_2rK2vKHZzW5RN6DtqpnvJv51IsnGTDyO_DYlPaIqikcje1HzYI7FcKJPosQTtupEvgF00-lqEw\", \"29bFyQIeGXDyhBLK7EzyXblSuekoGwy67NvXXgVHoQ2alRl1QI6ArqZ9XJprZSAdRN7huGaxTueVTQ\", \"-S7b-bptgLG8pvZ6zlOSGnXABjwdGsRdJ5Opa1hmIR0nC6XFrfHcuAtPQt8Ernrw5tk4UzsBur9DnQ\", \"1SG1L6AAUUH9VIMzvDyUa0RB4x94bm6q1dWZOBhtmp3qsxpLg381nD_HyLu6F3PXA0tRFM-y6jbxug\"]",
        "matchdata":"[{\"Champ\": \"Sett\", \"kills\": 9, \"deaths\": 4, \"assists\": 5, \"sumName\": \"ballsmoker\", \"champLevel\": 18, \"goldEarned\": 19254, \"playerTeamID\": 100}, {\"Champ\": \"Morgana\", \"kills\": 4, \"deaths\": 6, \"assists\": 7, \"sumName\": \"Nephrite\", \"champLevel\": 17, \"goldEarned\": 14552, \"playerTeamID\": 100}, {\"Champ\": \"Ekko\", \"kills\": 6, \"deaths\": 5, \"assists\": 3, \"sumName\": \"Chaddam\", \"champLevel\": 18, \"goldEarned\": 15304, \"playerTeamID\": 100}, {\"Champ\": \"Jinx\", 
\"kills\": 6, \"deaths\": 5, \"assists\": 5, \"sumName\": \"yiqii\", \"champLevel\": 17, \"goldEarned\": 15102, \"playerTeamID\": 100}, {\"Champ\": \"Renata\", \"kills\": 1, \"deaths\": 3, \"assists\": 9, \"sumName\": \"paul54435\", \"champLevel\": 14, \"goldEarned\": 8798, \"playerTeamID\": 100}, {\"Champ\": \"Garen\", \"kills\": 2, \"deaths\": 9, \"assists\": 4, \"sumName\": \"MELSSCRIT\", \"champLevel\": 18, \"goldEarned\": 16817, \"playerTeamID\": 200}, {\"Champ\": \"Udyr\", \"kills\": 4, \"deaths\": 3, \"assists\": 7, \"sumName\": \"Jordan Chan\", \"champLevel\": 18, \"goldEarned\": 14995, \"playerTeamID\": 200}, {\"Champ\": \"Zed\", \"kills\": 12, \"deaths\": 6, \"assists\": 6, \"sumName\": \"stemy v2\", \"champLevel\": 18, \"goldEarned\": 20517, \"playerTeamID\": 200}, {\"Champ\": \"Lucian\", \"kills\": 4, \"deaths\": 7, \"assists\": 6, \"sumName\": \"a perfect storm\", \"champLevel\": 18, \"goldEarned\": 15997, \"playerTeamID\": 200}, {\"Champ\": \"Milio\", \"kills\": 1, \"deaths\": 1, \"assists\": 16, \"sumName\": \"Lobotomize2\", \"champLevel\": 15, \"goldEarned\": 10383, \"playerTeamID\": 200}]"
    },
    {
        "gameID":"NA1_4794708129",
        "gameVer":"13.19.534.5972",
        "gameDurationMinutes":"25:34",
        "gameCreationTimestamp":"1696792433101",
        "gameEndTimestamp":"1696793989443",
        "participants":"[\"vuO44O8p56cnbIMysNlNMiz11a9WsFmOl8NBYaQeeeNCZwIfeBE9oG0Bvm3Kq-OXvpCa_Y_g5RB0_w\", \"nj83_D2T7Q0PZ32cnH7V9Z36_4Tz-V5wtgrojnfU_qC8DqCz5uM1tetF-JETE6yUi4EkegBxnTxtaQ\", \"Z37xqFKgX8gSakD40Yy4xDe2DSXzTNHKXKMRepONVSRzVHinFp0dBHBglLqyA4197ACZThIpfUHD3w\", \"rKdVolAV4X-JOUfvlnIiNx2RziM9bo2QZSktycKb_t5XU5BeQtULutCMPePipZeeO4KhE88_PQWJMg\", \"tN3MxzDXCWqh6hF1AusUQuHuIufVqePJ8My-v556szqNi118va9bIGtZy_c2x-2zLNMdKLyLUkZFTQ\", \"zertNS2qFbhVFNc_qI6UUbkY2apg8QDiXmreenX4S1e1vRzRMjobDTAu0C_x6erZ2Wa981dVAHn6Og\", \"CJlfSH-8uEcwx9kkx4nMEnp8UcGGN_UjlwC7DF8zNeJbs0fSpkrCaKu8Wm7vFbMepXeN_c5VFy6hug\", \"K98iyuDBR8uxwPa9oV82iOXP4DQFwtbL7Wu4fOlk_mpK3HpAxr7af_-aykzxP8OFN9B6gbdQDEW11g\", \"2COgeHTa0XScrbchc9RuOxGTEsVioIwo-NzTIEAMwIY3lMJ--66426Ubg645M9j2m0xnUzajS04pCA\", \"95q-EjUbRIvOtpDchU1fHmhgKEZ_zMUfM_RS7p9sX-KnO1Y0mdnxzuzX-F3Wvx8rqOhwFHVL-Vx1hw\"]",
        "matchdata":"[{\"Champ\": \"Hecarim\", \"kills\": 3, \"deaths\": 5, \"assists\": 3, \"sumName\": \"Horse Goes Vroom\", \"champLevel\": 12, \"goldEarned\": 8368, \"playerTeamID\": 100}, {\"Champ\": \"Tryndamere\", \"kills\": 1, \"deaths\": 5, \"assists\": 2, \"sumName\": \"futtbucker96\", \"champLevel\": 15, \"goldEarned\": 9987, \"playerTeamID\": 100}, {\"Champ\": \"Vex\", \"kills\": 3, \"deaths\": 4, \"assists\": 2, \"sumName\": \"Its Big Man Zach\", \"champLevel\": 14, \"goldEarned\": 8750, \"playerTeamID\": 100}, {\"Champ\": \"Vayne\", \"kills\": 8, \"deaths\": 6, \"assists\": 2, \"sumName\": \"Lemon 1\", \"champLevel\": 11, \"goldEarned\": 10071, \"playerTeamID\": 100}, {\"Champ\": \"Thresh\", \"kills\": 0, \"deaths\": 7, \"assists\": 8, \"sumName\": \"Flashdash11\", \"champLevel\": 10, \"goldEarned\": 6081, \"playerTeamID\": 100}, {\"Champ\": \"Malphite\", \"kills\": 4, \"deaths\": 1, \"assists\": 9, \"sumName\": \"JerryJX\", \"champLevel\": 16, \"goldEarned\": 11667, \"playerTeamID\": 200}, {\"Champ\": \"Shaco\", \"kills\": 11, \"deaths\": 2, \"assists\": 6, \"sumName\": \"Nephrite\", \"champLevel\": 15, \"goldEarned\": 12988, \"playerTeamID\": 200}, {\"Champ\": \"Ekko\", \"kills\": 4, \"deaths\": 5, \"assists\": 5, \"sumName\": \"Chaddam\", \"champLevel\": 15, \"goldEarned\": 11478, \"playerTeamID\": 200}, {\"Champ\": \"Jhin\", \"kills\": 3, \"deaths\": 5, \"assists\": 10, \"sumName\": \"Madeu ina heaven\", \"champLevel\": 12, \"goldEarned\": 9621, \"playerTeamID\": 200}, {\"Champ\": \"Yuumi\", \"kills\": 5, \"deaths\": 2, \"assists\": 16, \"sumName\": \"Brelshaza\", \"champLevel\": 13, \"goldEarned\": 8971, \"playerTeamID\": 200}]"
    },
    {
        "gameID":"NA1_4794677136",
        "gameVer":"13.19.534.5972",
        "gameDurationMinutes":"25:28",
        "gameCreationTimestamp":"1696789950539",
        "gameEndTimestamp":"1696791547113",
        "participants":"[\"TFlKG6LCDLt1Wsihm2MA_Dx5LjD_49nlH_AvTNfS8x4cHzmXUaa8FxEviOYRzmzfzcqjqWsEfHJanw\", \"CJlfSH-8uEcwx9kkx4nMEnp8UcGGN_UjlwC7DF8zNeJbs0fSpkrCaKu8Wm7vFbMepXeN_c5VFy6hug\", \"K98iyuDBR8uxwPa9oV82iOXP4DQFwtbL7Wu4fOlk_mpK3HpAxr7af_-aykzxP8OFN9B6gbdQDEW11g\", \"bDPby43niT0X3cFW9sjm2WcngOtLILDPwBNy7FHnDYe_azp80i04sexK400Pg_ACUlFFJezZI6k4aw\", \"IaGcUGyAM0JG26DoALhQklCpLEYVFEXiYNtjjmFM2driT-ucIDcM3Ci05vOKjoqN15-UgcwTNvEvSw\", \"6_3XlvF9Jea0bBna1a6_LpfpzuQShNvh7S0-fA9mVun1czJJ9UoTxOP9hLlE8vLTBTejEAhvIR_NCQ\", \"Wa4oM5zgJAtXF7jNdYXcYyhj4ThcNwcwkY_7sLB0OcOuxQFW9zp6UyXMvJY9-QmvESJhfgBdMXshIQ\", \"MzPinfE5dofye3PjVyQ_KNRra5P4NzBpG9Nj57VmvJ4WWnyMKPRMzUgYY_UzSJRdPK8jm6HqiORL7A\", \"NB78L8hzAD2TYCbUaSTfrvKFtyd4rNZCsuqWsCSNDt3Ha3CD5ijQG4vZkexHdbhcVIOQtlTII8bS9Q\", \"9sG6UL_K3hNJO5gDxvxoyPOURk6gnvD-1MPePpbRE4l-PyAwMXss3YC66ouYUjGIX0NIbr8DNYg2Kw\"]",
        "matchdata":"[{\"Champ\": \"Poppy\", \"kills\": 7, \"deaths\": 2, \"assists\": 1, \"sumName\": \"EternalJ\", \"champLevel\": 16, \"goldEarned\": 11648, \"playerTeamID\": 100}, {\"Champ\": \"Ivern\", \"kills\": 3, \"deaths\": 3, \"assists\": 7, \"sumName\": \"Nephrite\", \"champLevel\": 14, \"goldEarned\": 9661, \"playerTeamID\": 100}, {\"Champ\": \"Ekko\", \"kills\": 11, \"deaths\": 3, \"assists\": 4, \"sumName\": \"Chaddam\", \"champLevel\": 17, \"goldEarned\": 13719, \"playerTeamID\": 100}, {\"Champ\": \"Ezreal\", \"kills\": 4, \"deaths\": 3, \"assists\": 3, \"sumName\": \"CritDaddy\", \"champLevel\": 13, \"goldEarned\": 11007, \"playerTeamID\": 100}, {\"Champ\": \"Yuumi\", \"kills\": 1, \"deaths\": 1, \"assists\": 7, \"sumName\": \"PaulineLaCoquine\", \"champLevel\": 12, \"goldEarned\": 6652, \"playerTeamID\": 100}, {\"Champ\": \"Briar\", \"kills\": 2, \"deaths\": 10, \"assists\": 3, \"sumName\": \"zzkool\", \"champLevel\": 13, \"goldEarned\": 7709, \"playerTeamID\": 200}, {\"Champ\": \"Lillia\", \"kills\": 2, \"deaths\": 5, \"assists\": 3, \"sumName\": \"Peluzø\", \"champLevel\": 12, \"goldEarned\": 8770, \"playerTeamID\": 200}, {\"Champ\": \"Ahri\", \"kills\": 4, \"deaths\": 3, \"assists\": 3, \"sumName\": \"Thyopus\", \"champLevel\": 14, \"goldEarned\": 9575, \"playerTeamID\": 200}, {\"Champ\": \"Nilah\", \"kills\": 1, \"deaths\": 7, \"assists\": 2, \"sumName\": \"Ruinutty\", \"champLevel\": 12, \"goldEarned\": 8721, \"playerTeamID\": 200}, {\"Champ\": \"Karma\", \"kills\": 3, \"deaths\": 1, \"assists\": 3, \"sumName\": \"Uxiee\", \"champLevel\": 12, \"goldEarned\": 6983, \"playerTeamID\": 200}]"
    },
    {
        "gameID":"NA1_4792810286",
        "gameVer":"13.19.534.5972",
        "gameDurationMinutes":"24:39",
        "gameCreationTimestamp":"1696626258452",
        "gameEndTimestamp":"1696627788725",
        "participants":"[\"zmRV-qr2AyvicOUy1bA3uZ03N4bk2bhD3dz9u8jVj9ShtzdYNf1VjkF3ZbhveUsJtpk8HqtgA1_xhw\", \"CJlfSH-8uEcwx9kkx4nMEnp8UcGGN_UjlwC7DF8zNeJbs0fSpkrCaKu8Wm7vFbMepXeN_c5VFy6hug\", \"K98iyuDBR8uxwPa9oV82iOXP4DQFwtbL7Wu4fOlk_mpK3HpAxr7af_-aykzxP8OFN9B6gbdQDEW11g\", \"6w3-8beTCDu_flCMsfy12QyTesZGV7BDKcwMDm47IGCFKl7Gt-WUvfuzvqF_B4aYQQuODGBM1KOHXg\", \"JV4CCV1RIxbT3r6R-4ydd5Z6MZdaFM7g79Nl5MPuuGHhp2i6z9DJ6r8aGGLMwmca-FtmR5xaMw1hAg\", \"paYvdVpSmQJFZE3K3PUsfYAIhf7wdYmwNfY3ScRxBJ63otkPwRFkG7dZJqZwlag8Th533v7Ra4cBvw\", \"5um2VEPoVcSY7U4ZWOoKgd_CQMakltkUh-bGzBE7eyW3c6_omCGFE_QDUeotQtOkkjs6GHR1x19cEA\", \"10ARmUVMOmqC3c-256xSLyunva_I4O92OdK2mZQcoubQbbZHObRewWqPJpwlskzXl8Tcymjh9o7zIg\", \"0ODxKf4z7l7ilnT2l1SaMlkmi8-KYXXGQqMC-aykUP9UHuMJni8Qlw93F1ZCjS9MRBREFUcc5CYLLQ\", 
\"uyohMQYoI0fKHq7SSuLwIuLFRkejC35s-GzAcYsJwANYvK2bBjP1_cO-6TFTjRBzu0wBJDVDCwZtKw\"]",
        "matchdata":"[{\"Champ\": \"Aatrox\", \"kills\": 1, \"deaths\": 8, \"assists\": 3, \"sumName\": \"iTunes\", \"champLevel\": 12, \"goldEarned\": 6522, \"playerTeamID\": 100}, {\"Champ\": \"Ivern\", 
\"kills\": 2, \"deaths\": 11, \"assists\": 11, \"sumName\": \"Nephrite\", \"champLevel\": 12, \"goldEarned\": 7727, \"playerTeamID\": 100}, {\"Champ\": \"Ekko\", \"kills\": 12, \"deaths\": 8, \"assists\": 1, \"sumName\": \"Chaddam\", \"champLevel\": 15, \"goldEarned\": 14267, \"playerTeamID\": 100}, {\"Champ\": \"Kaisa\", \"kills\": 4, \"deaths\": 10, \"assists\": 3, \"sumName\": \"AnXayahties\", \"champLevel\": 13, \"goldEarned\": 9962, \"playerTeamID\": 100}, {\"Champ\": \"Bard\", \"kills\": 2, \"deaths\": 10, \"assists\": 10, \"sumName\": \"Saboodles\", \"champLevel\": 12, \"goldEarned\": 6409, \"playerTeamID\": 100}, {\"Champ\": \"Zed\", \"kills\": 12, \"deaths\": 3, \"assists\": 8, \"sumName\": \"Daddy ZED99\", \"champLevel\": 16, \"goldEarned\": 15405, \"playerTeamID\": 200}, {\"Champ\": \"Briar\", \"kills\": 10, \"deaths\": 6, \"assists\": 10, \"sumName\": \"TheeBeast\", \"champLevel\": 14, \"goldEarned\": 12928, \"playerTeamID\": 200}, {\"Champ\": \"Fizz\", \"kills\": 4, \"deaths\": 5, \"assists\": 10, \"sumName\": \"G3POPOY\", \"champLevel\": 14, \"goldEarned\": 10301, \"playerTeamID\": 200}, {\"Champ\": \"Samira\", \"kills\": 15, \"deaths\": 4, \"assists\": 6, \"sumName\": \"pornymcdorny\", \"champLevel\": 13, \"goldEarned\": 14023, \"playerTeamID\": 200}, {\"Champ\": \"Lux\", \"kills\": 6, \"deaths\": 3, \"assists\": 21, \"sumName\": \"Pirate of Candy\", \"champLevel\": 12, \"goldEarned\": 9902, \"playerTeamID\": 200}]"
    },
    {
        "gameID":"NA1_4792784632",
        "gameVer":"13.19.534.5972",
        "gameDurationMinutes":"25:53",
        "gameCreationTimestamp":"1696624333821",
        "gameEndTimestamp":"1696625916669",
        "participants":"[\"l-d6VaVROvEM-ztgE3yvXGCy_rIUTRljt-HHb_tBTVDnoW5CP04HCKQtg70I-bV5SVLdoyOCRxj3AQ\", \"uB4FUtdtvKezQlA35MhKjTAY6b6ZPZVrdMJlTy8itzn7RaMgy64keRoiVelGKosHjne4KGy0Q0Jxyw\", \"qJflIp3aETtpfKMCJtx2ftC2EbTkPxofExzjSDt9zMQD-JOWaY-j1LVRGkbAVtVNaTctNdgxbQxQYw\", \"ruyMKvh-uqRCT1AlbjIUiMk23RG7tIcLUsDf_kCQt19pvoF_YjkUo7n6T4UarTUZZYLX3EBcNZyh-w\", \"KQYhY-5NV483kn89TY5V14rubbrpZFZDGbe7CXXTjfNyVe0sFxuGnJHOHQ7yLZ-Eybu0-73TKawDrA\", \"6uZOoDOi-YuMsR9qS3EcE33Qi2I5NkIOUxue59VRpM_hbentMZZFmHAgcAWS3ztconG5myX299e4DQ\", \"CJlfSH-8uEcwx9kkx4nMEnp8UcGGN_UjlwC7DF8zNeJbs0fSpkrCaKu8Wm7vFbMepXeN_c5VFy6hug\", \"K98iyuDBR8uxwPa9oV82iOXP4DQFwtbL7Wu4fOlk_mpK3HpAxr7af_-aykzxP8OFN9B6gbdQDEW11g\", \"sRS8VS5_zzdkhzlm-OvCQOdl2xTVnZsq5gB3c9D-M1DuQr6T7NA5s_Kh4c4syzKWdGeVeBGs7Iv8kQ\", \"XXr7OxhVsY3y12FJ-GDV4k2mzUjtatMy8TOESHEVuj5QJE-o2EmezoGG7yOdsrGWF7i98QbuZJf-sg\"]",
        "matchdata":"[{\"Champ\": \"KSante\", \"kills\": 4, \"deaths\": 6, \"assists\": 5, \"sumName\": \"how far ive come\", \"champLevel\": 14, \"goldEarned\": 10146, \"playerTeamID\": 100}, {\"Champ\": \"JarvanIV\", \"kills\": 4, \"deaths\": 7, \"assists\": 5, \"sumName\": \"TheGoldenChamp\", \"champLevel\": 13, \"goldEarned\": 9821, \"playerTeamID\": 100}, {\"Champ\": \"Fizz\", \"kills\": 6, \"deaths\": 7, \"assists\": 7, \"sumName\": \"Eren03\", \"champLevel\": 13, \"goldEarned\": 11020, \"playerTeamID\": 100}, {\"Champ\": \"Jhin\", \"kills\": 5, \"deaths\": 8, \"assists\": 2, \"sumName\": \"Young Tiller\", \"champLevel\": 12, \"goldEarned\": 9800, \"playerTeamID\": 100}, {\"Champ\": \"Nami\", \"kills\": 0, \"deaths\": 6, \"assists\": 10, \"sumName\": \"buhari\", \"champLevel\": 11, \"goldEarned\": 6162, \"playerTeamID\": 100}, {\"Champ\": \"Tryndamere\", \"kills\": 6, \"deaths\": 5, \"assists\": 7, \"sumName\": \"leeslee\", \"champLevel\": 16, \"goldEarned\": 11773, \"playerTeamID\": 200}, {\"Champ\": \"Ivern\", \"kills\": 3, \"deaths\": 2, \"assists\": 12, \"sumName\": \"Nephrite\", \"champLevel\": 15, \"goldEarned\": 10902, \"playerTeamID\": 200}, {\"Champ\": \"Ekko\", \"kills\": 8, \"deaths\": 4, \"assists\": 4, \"sumName\": \"Chaddam\", \"champLevel\": 15, \"goldEarned\": 12608, \"playerTeamID\": 200}, {\"Champ\": \"Kaisa\", \"kills\": 14, \"deaths\": 5, \"assists\": 7, \"sumName\": \"Lunari Xll\", \"champLevel\": 15, \"goldEarned\": 14540, \"playerTeamID\": 200}, {\"Champ\": 
\"Blitzcrank\", \"kills\": 2, \"deaths\": 3, \"assists\": 20, \"sumName\": \"Neck Beard NA\", \"champLevel\": 13, \"goldEarned\": 8073, \"playerTeamID\": 200}]"
    },
    {
        "gameID":"NA1_4792317198",
        "gameVer":"13.19.534.5972",
        "gameDurationMinutes":"33:15",
        "gameCreationTimestamp":"1696565532969",
        "gameEndTimestamp":"1696567544945",
        "participants":"[\"Vh8IyQFPzF7qhnObNjYI10CKhecdnc-z2nrwLm9zEKFgjL-h9uGyT_WTTjg4tFFhpeKJ7TqFiMsGqQ\", \"0o0afoz7PzuWVVsBto9gyDP6QyKBzIfxc5cvqAz-YCxnA9So4JizlPwCTbcF-OSHUoAtM4rWyN3P9g\", \"K98iyuDBR8uxwPa9oV82iOXP4DQFwtbL7Wu4fOlk_mpK3HpAxr7af_-aykzxP8OFN9B6gbdQDEW11g\", \"bHjL8_QLJTaPYJdv2GtP0tpVwz1r6BHB4XZfdb095_XKney7IAqDocfneZZMOMr4CDTIW639r44Faw\", \"N7QO2P2ugNEaWOywv_xdx-CrsykYwQlZQDPWGoCzltoIU7U1Y2PL2BEJlultPr9PGXhAZUMro6kN5Q\", \"WrIh2H3AY6svh1NixjDDpkdGhI5vz4acWb23DTp8RLMvqpBRe3qSFMqXvgaKNvYhCtHXrsSSm-l1aA\", \"YpyuVgT6rOeAB6eg4BgUiTJZmLgqkUHshm3Z4WXCGnZ5g5W01GQPJSMHhSrOmlm5zj-I7dKHyba1lQ\", \"Z8ZG1TwX4Q0cN005e138wZjK88o0rDsudwdpjdSD5VL0_1r1J9E69BvMIAWDKa2OiTCedlD6HwUgaw\", \"QvzqWwGnO8K-TBvBaov3DM335ruyDZwswM_23ZtCJjUuzq8YEIe-EjyCPfW9HI6BIBMnsDqX7wp8OA\", \"9f9qDYL9lIwvrEXQjlcu6CvT7fOOPFdOSB8hFEjJ_OcbLSczQqEjWC76Y4tBZyJPs_XDFkhQxEu5vQ\"]",
        "matchdata":"[{\"Champ\": \"Volibear\", \"kills\": 1, \"deaths\": 8, \"assists\": 12, \"sumName\": \"andyblacksock\", \"champLevel\": 16, \"goldEarned\": 11521, \"playerTeamID\": 100}, {\"Champ\": \"Briar\", \"kills\": 11, \"deaths\": 11, \"assists\": 7, \"sumName\": \"oaoalcb\", \"champLevel\": 17, \"goldEarned\": 15735, \"playerTeamID\": 100}, {\"Champ\": \"Ekko\", \"kills\": 13, \"deaths\": 4, \"assists\": 6, \"sumName\": \"Chaddam\", \"champLevel\": 18, \"goldEarned\": 17305, \"playerTeamID\": 100}, {\"Champ\": \"MissFortune\", \"kills\": 7, \"deaths\": 10, \"assists\": 5, \"sumName\": \"lbwnb666\", \"champLevel\": 15, \"goldEarned\": 14925, \"playerTeamID\": 100}, {\"Champ\": \"Alistar\", \"kills\": 2, \"deaths\": 5, \"assists\": 17, \"sumName\": \"PuffyNippIes\", \"champLevel\": 14, \"goldEarned\": 8419, \"playerTeamID\": 100}, {\"Champ\": \"Akshan\", \"kills\": 15, \"deaths\": 11, \"assists\": 11, \"sumName\": \"Lee Sín\", \"champLevel\": 17, \"goldEarned\": 17990, \"playerTeamID\": 200}, {\"Champ\": \"Maokai\", \"kills\": 6, \"deaths\": 5, \"assists\": 16, \"sumName\": \"Lil Zutter\", \"champLevel\": 16, \"goldEarned\": 15540, \"playerTeamID\": 200}, {\"Champ\": \"Pantheon\", \"kills\": 11, \"deaths\": 4, \"assists\": 5, \"sumName\": \"Death Of A Dream\", \"champLevel\": 17, \"goldEarned\": 14410, \"playerTeamID\": 200}, {\"Champ\": \"Seraphine\", \"kills\": 4, \"deaths\": 9, \"assists\": 20, \"sumName\": \"mason margiela\", \"champLevel\": 16, \"goldEarned\": 12237, \"playerTeamID\": 200}, {\"Champ\": \"Senna\", \"kills\": 2, \"deaths\": 5, \"assists\": 26, \"sumName\": \"Shinichiwa\", \"champLevel\": 15, \"goldEarned\": 11123, \"playerTeamID\": 200}]"
    },
    {
        "gameID":"NA1_4792277329",
        "gameVer":"13.19.534.5972",
        "gameDurationMinutes":"24:21",
        "gameCreationTimestamp":"1696563430350",
        "gameEndTimestamp":"1696564917154",
        "participants":"[\"dWRa0X9eYsNfy3-R6sGLcALsfJfzXUInBv9U7XokhFHrD0qPhMKqn8o4BVOpH6FXusaMKwTomjIEsw\", \"pR3h4sYm1UV8uPZE89R_yF7MXdbe6lvKZ5ztRkLR_qnTrqPz3dCqJ_PSGKIazlFU2Bt-zJlhWN0lEA\", \"K98iyuDBR8uxwPa9oV82iOXP4DQFwtbL7Wu4fOlk_mpK3HpAxr7af_-aykzxP8OFN9B6gbdQDEW11g\", \"yfXpGZs_IsjJAasnsgaYqBcyvlZdsegKakJ8Eq1YC7OqVi8HTYPVaEnxpG-7XoXbsnok2BzgIBSeZQ\", \"ZwBoVEAM_iPLgwIuNwZG6CBluXoOjwIoyQdxzTw0Ke8lWLBMkL3e7PfB1Vz-YzQUvs44Ig_ctcvrZA\", \"VvpPSNcD85z_l7Lhf11NGBPZiwMIDNSP1g5-_1GZn2Zw9Asvg4gbRL65rgQQBIAch_B8q6LlfMv6-w\", \"a5Y0aXaXmG4vSMX9ztcCJvFl_t-uqZiyoCN37OAvKcY1yNC5BsVPvUi6CjCb_IuruuO9l_oPNTjkaw\", \"nHeGiW-BGdRfcyQQmLbq9CThFCxCbI4R-R1qRMI74LQzi1mQ2zliYCY5YRHSUuzk1hVwe8aZSPUBnA\", \"cljWEjLg3Q04uBcbd4lKJws6jhVtuUjS9dI2IsiH9MuURmkATYDK0Y_-pIDPIjKIamYUUK__Q42DdA\", \"cYOUFIdc-xcx2gJcNEOrqlto-hFC5rbwkiMPn_Wv-ph_RP-smuUtsGxc8kE7OtpY3o8Y2waru5IP7A\"]",
        "matchdata":"[{\"Champ\": \"Chogath\", \"kills\": 7, \"deaths\": 2, \"assists\": 3, \"sumName\": \"Dannieboi\", \"champLevel\": 15, \"goldEarned\": 11416, \"playerTeamID\": 100}, {\"Champ\": \"Khazix\", \"kills\": 10, \"deaths\": 2, \"assists\": 5, \"sumName\": \"12XU\", \"champLevel\": 14, \"goldEarned\": 12937, \"playerTeamID\": 100}, {\"Champ\": \"Ekko\", \"kills\": 6, \"deaths\": 2, 
\"assists\": 7, \"sumName\": \"Chaddam\", \"champLevel\": 15, \"goldEarned\": 11609, \"playerTeamID\": 100}, {\"Champ\": \"Ezreal\", \"kills\": 4, 
\"deaths\": 2, \"assists\": 8, \"sumName\": \"JD Drew Man 2\", \"champLevel\": 12, \"goldEarned\": 9028, \"playerTeamID\": 100}, {\"Champ\": \"Karma\", \"kills\": 3, \"deaths\": 1, \"assists\": 10, \"sumName\": \"Vestia\", \"champLevel\": 12, \"goldEarned\": 7847, \"playerTeamID\": 100}, {\"Champ\": \"Leblanc\", \"kills\": 1, \"deaths\": 6, \"assists\": 1, \"sumName\": \"Delilah\", \"champLevel\": 14, \"goldEarned\": 9237, \"playerTeamID\": 200}, {\"Champ\": \"Sejuani\", \"kills\": 2, \"deaths\": 8, \"assists\": 3, \"sumName\": \"CactusBill\", \"champLevel\": 12, \"goldEarned\": 9044, \"playerTeamID\": 200}, {\"Champ\": \"Teemo\", \"kills\": 4, \"deaths\": 7, \"assists\": 0, \"sumName\": \"Yiaze\", \"champLevel\": 13, \"goldEarned\": 9460, \"playerTeamID\": 200}, {\"Champ\": \"KogMaw\", \"kills\": 2, \"deaths\": 5, \"assists\": 1, \"sumName\": \"Zlordz\", \"champLevel\": 
11, \"goldEarned\": 7057, \"playerTeamID\": 200}, {\"Champ\": \"Lulu\", \"kills\": 0, \"deaths\": 4, \"assists\": 4, \"sumName\": \"fanxiss\", \"champLevel\": 11, \"goldEarned\": 5532, \"playerTeamID\": 200}]"
    },
    {
        "gameID":"NA1_4792220472",
        "gameVer":"13.19.534.5972",
        "gameDurationMinutes":"37:39",
        "gameCreationTimestamp":"1696560489751",
        "gameEndTimestamp":"1696562794784",
        "participants":"[\"hkdHh3lKjF6sB23H_s50WPExNCm5DPAtxDP0UzMIoxzCFG4XHWF6o1MZqBVWe4B64kIbt2W-MKbTzw\", \"RU_C84tyoLGFR6dHBpv0yOyNTjR9FJegSiXOQ-Na11-JvlAoHYbOaMq3TfkbEiR3fVH4sFVKhbyYrA\", \"FF2R0JElR-mE3Vo4EJSfSSvpOZIWFDYTmVeBW4XQt9QQ6xBYQe3Wq1i0bLQDMZU2pdNX7hktwRyC3Q\", \"gaXgWhRFP-l_YI_6D1mLtFT7Te8CgiMoTA3BiIrByZlS3-OlZiT8CwDaxct7_p2iU81BSMPVsgFwyQ\", \"Zx-k08pGHQTZV82Vg1gI-wNfSsFGRFovWQ6JroEpy82V8MknjWDNeA3hi2q8vunHihjiOa6McIV73A\", \"G2nQuLp188UeXBJ2Gsf5qrIRoOqfpE6dVVSmROvLfV3E66UflUTTQOEfcPdq8Cj62FNqbUVxpCxqfA\", \"WAugfGKBPU_H9phIn35rvz4CHHhPhSxyoslGw_fQMxSAllmYVY5Qw4P6ppAc_lmdq3ceCn3RgDbq4Q\", \"K98iyuDBR8uxwPa9oV82iOXP4DQFwtbL7Wu4fOlk_mpK3HpAxr7af_-aykzxP8OFN9B6gbdQDEW11g\", \"Z4gJLYDj1nnJchaczbjp9OygT6ewm64fCCttsduDm7ywkG3fHWXDe0ZK6Inke2OfbcbxR0EZiCJLqw\", \"EHET0ZFmROnv_Rh00mrVSIXC-KKTTQx0ZV6Igf4IzSwAxvuxeqiuk51mB9N5qZYXDUr176p5ScrLAA\"]",
        "matchdata":"[{\"Champ\": \"Garen\", \"kills\": 9, \"deaths\": 7, \"assists\": 7, \"sumName\": \"GORILLAM0\", \"champLevel\": 18, \"goldEarned\": 16650, \"playerTeamID\": 100}, {\"Champ\": \"Briar\", \"kills\": 13, \"deaths\": 8, \"assists\": 8, \"sumName\": \"Ive Been Doin Me\", \"champLevel\": 18, \"goldEarned\": 17474, \"playerTeamID\": 100}, {\"Champ\": \"Syndra\", \"kills\": 10, \"deaths\": 6, \"assists\": 15, \"sumName\": \"shades of cool\", \"champLevel\": 17, \"goldEarned\": 15174, \"playerTeamID\": 100}, {\"Champ\": \"Jhin\", \"kills\": 15, \"deaths\": 3, \"assists\": 18, \"sumName\": \"Toulki\", \"champLevel\": 18, \"goldEarned\": 18878, \"playerTeamID\": 100}, {\"Champ\": \"Janna\", \"kills\": 1, \"deaths\": 7, \"assists\": 31, \"sumName\": \"Spirit Water\", \"champLevel\": 16, \"goldEarned\": 10249, \"playerTeamID\": 100}, {\"Champ\": \"Tryndamere\", \"kills\": 12, \"deaths\": 8, \"assists\": 4, \"sumName\": \"Alenn\", \"champLevel\": 18, \"goldEarned\": 21686, \"playerTeamID\": 200}, {\"Champ\": \"Belveth\", \"kills\": 4, \"deaths\": 10, \"assists\": 11, \"sumName\": \"Dont Wanna Alone\", \"champLevel\": 16, \"goldEarned\": 13446, \"playerTeamID\": 200}, {\"Champ\": \"Ekko\", \"kills\": 12, \"deaths\": 8, \"assists\": 7, \"sumName\": \"Chaddam\", \"champLevel\": 18, \"goldEarned\": 18304, \"playerTeamID\": 200}, {\"Champ\": \"Kaisa\", \"kills\": 2, \"deaths\": 11, \"assists\": 8, \"sumName\": \"02 june\", \"champLevel\": 16, \"goldEarned\": 13936, \"playerTeamID\": 200}, {\"Champ\": \"Thresh\", \"kills\": 1, \"deaths\": 11, \"assists\": 9, \"sumName\": \"Thresh Hooker\", \"champLevel\": 15, \"goldEarned\": 9327, \"playerTeamID\": 200}]"
    },
    {
        "gameID":"NA1_4792085407",
        "gameVer":"13.19.534.5972",
        "gameDurationMinutes":"30:56",
        "gameCreationTimestamp":"1696553003800",
        "gameEndTimestamp":"1696554941413",
        "participants":"[\"xjUe9TC6qH-zwrUtkqvVp1BbxK10Cutsdy1n7DDZsYwYRYb-wsiAE1cGB-Pp19yT7kjM9EZl58ff7g\", \"EVs__vssHZFdYg9bJJr-oNsEs7FFEMHaZ4Luz1ytQa3FYhaO43vFHx9VDVT3Rmo1lvidqdHFg5homg\", \"K98iyuDBR8uxwPa9oV82iOXP4DQFwtbL7Wu4fOlk_mpK3HpAxr7af_-aykzxP8OFN9B6gbdQDEW11g\", \"xJaNfMPchQRj-tOYXJUsZ5XKyAPguhU6ZkFM-0czHLNUqqSqxwlKsoVXoYuMNl_6Ml7q7mt1QlXigg\", \"dQAPenBKpdkrdZ5voeNjEj1qGf_1XVMO0hub61d6nKw4J7_bz2fC04Q1UFWk1jhNnISB9mo3b9Ev-Q\", \"aLITOidDbfUbjefOpzVAasXbtq1DHLvJ1mw1zrFl7z9ADU1xj0ze5TUoQNn1lFDEEc5mMqETTDMwFA\", \"yDk5PUQjVU_36uZwYfLowS-b9R3_8nSiDVJWE5lrAVU61FZ5-Yn8CUqfsyAbxqcJSyaGZ_M63kEa6g\", \"JoejCjyvxGhr8tOkk6O2u_0lB9WjHXQSvbNs5-ZJBPvvQzLOtWdLPT2yYUIrZ1iIJfSvfRSUyrwhwQ\", \"B-e6vUrREUDQkvPGglcY4hq0PlS_OujjqI-OzYR3IXzOqZQJX02VJZE8odeOD_GPY634xaZpiqG1Ag\", \"Ar1PmJRa6uH4kGszW-amlfEI5dl_1E-8d-dlrqmoDOJZyJ5N22S4b__Ph3lExtvqSHKZWRIf-hMLCg\"]",
        "matchdata":"[{\"Champ\": \"Singed\", \"kills\": 7, \"deaths\": 4, \"assists\": 8, \"sumName\": \"SteveSteveck\", \"champLevel\": 18, \"goldEarned\": 14600, \"playerTeamID\": 100}, {\"Champ\": \"Khazix\", \"kills\": 15, \"deaths\": 6, \"assists\": 10, \"sumName\": \"T00MY\", \"champLevel\": 18, \"goldEarned\": 18219, \"playerTeamID\": 100}, {\"Champ\": \"Ekko\", \"kills\": 5, \"deaths\": 4, \"assists\": 7, \"sumName\": \"Chaddam\", \"champLevel\": 17, \"goldEarned\": 14897, \"playerTeamID\": 100}, {\"Champ\": \"Jinx\", \"kills\": 2, \"deaths\": 13, \"assists\": 11, \"sumName\": \"a very bad boy\", \"champLevel\": 13, \"goldEarned\": 10501, \"playerTeamID\": 100}, {\"Champ\": \"Swain\", \"kills\": 7, \"deaths\": 5, \"assists\": 18, \"sumName\": \"UnCane\", \"champLevel\": 15, \"goldEarned\": 12199, \"playerTeamID\": 100}, {\"Champ\": \"Yone\", \"kills\": 7, \"deaths\": 6, \"assists\": 6, \"sumName\": \"noypuP\", \"champLevel\": 18, \"goldEarned\": 17466, \"playerTeamID\": 200}, {\"Champ\": \"Nocturne\", \"kills\": 3, \"deaths\": 7, \"assists\": 10, \"sumName\": \"Lv1 Jaeguri\", \"champLevel\": 15, \"goldEarned\": 11634, \"playerTeamID\": 200}, {\"Champ\": \"Sylas\", \"kills\": 8, \"deaths\": 8, \"assists\": 4, \"sumName\": \"QkgdkTsp\", \"champLevel\": 15, \"goldEarned\": 11379, \"playerTeamID\": 200}, {\"Champ\": \"Samira\", \"kills\": 7, \"deaths\": 8, \"assists\": 10, \"sumName\": \"Winnabłe\", \"champLevel\": 14, \"goldEarned\": 12722, \"playerTeamID\": 200}, {\"Champ\": \"Blitzcrank\", \"kills\": 6, 
\"deaths\": 7, \"assists\": 11, \"sumName\": \"Mookins\", \"champLevel\": 13, \"goldEarned\": 8785, \"playerTeamID\": 200}]"
    },
    {
        "gameID":"NA1_4791676974",
        "gameVer":"13.19.534.5972",
        "gameDurationMinutes":"27:35",
        "gameCreationTimestamp":"1696502832958",
        "gameEndTimestamp":"1696504507429",
        "participants":"[\"9sCaboquse1_hLNrvABiL6EZgOFLfpU8br012cjROYAe7ivszKVU7o5__JIXaZeIdt0TlQI2YnLl2Q\", \"r6t-7uXK4P_Fkyqfg7WX_c8K78A1XI-Et55MSfmZCj7yHzGiBKKkBjKchm5eWyPTi-M3XvZEu7evUA\", \"K98iyuDBR8uxwPa9oV82iOXP4DQFwtbL7Wu4fOlk_mpK3HpAxr7af_-aykzxP8OFN9B6gbdQDEW11g\", \"pu4nX8V8Y1zNWXiKSYIuMOvLgxvBDLD8RJ16kQD7tiEJJumlNImdnNMe25oXSdei4KWNQdDpExpVoA\", \"QmJ8tWz3zruqMAsDEastqEcwz6HMCxkmGlWHibp-rceFDpRYva3OKZ4ySBr_iKf8yNQP9YxOoCqQug\", \"Prmusd5KBEA69PMsfiuH_U9AaHtG7TRoXQnR6hyv1ecrw8E-Da3oRKeY7wFq6K_i-Ik4Lm3IRIPD2Q\", \"wJHUdOmB5S_l7U74IwJp-2kX0NZuH9AzTo9LLp6tRIu5aq0BnUwjFswoNEWz5kmOxPs3bL8kUnndIg\", \"qVECMhH-i98oGcdk1vvnDCukTQniw0MrHD1Lf17MuBg3y-XdZrxPfxEc_4MT0r5uyzKhvYnNUdvGUQ\", \"hB9S3IQmU2T94kb845DNeyzSWNXPleHSaKHqUptH-k1xnQkz9S6d862rZVANXUgqJZZrX3iR5wecdg\", \"zZlUw0ARuBUZyo_0Mt9EqovtdZDgpE0OKgBcCmhHsOw0hJwqEzS9sDRTVtDhqq8KtijPPB-y1ZXCqA\"]",
        "matchdata":"[{\"Champ\": \"Fiora\", \"kills\": 3, \"deaths\": 8, \"assists\": 6, \"sumName\": \"8834760\", \"champLevel\": 15, \"goldEarned\": 10008, \"playerTeamID\": 100}, {\"Champ\": \"Rengar\", \"kills\": 9, \"deaths\": 3, \"assists\": 7, \"sumName\": \"Mcdonalds Murder\", \"champLevel\": 17, \"goldEarned\": 13574, \"playerTeamID\": 100}, {\"Champ\": \"Ekko\", \"kills\": 17, \"deaths\": 3, \"assists\": 4, \"sumName\": \"Chaddam\", \"champLevel\": 17, \"goldEarned\": 16787, 
\"playerTeamID\": 100}, {\"Champ\": \"Ashe\", \"kills\": 7, \"deaths\": 7, \"assists\": 4, \"sumName\": \"GOALIEmaster\", \"champLevel\": 14, \"goldEarned\": 10901, \"playerTeamID\": 100}, {\"Champ\": \"MissFortune\", \"kills\": 5, \"deaths\": 5, \"assists\": 10, \"sumName\": \"Blueberry Matcha\", \"champLevel\": 14, \"goldEarned\": 10377, \"playerTeamID\": 100}, {\"Champ\": \"Tryndamere\", \"kills\": 8, \"deaths\": 4, \"assists\": 1, 
\"sumName\": \"Seibastian\", \"champLevel\": 15, \"goldEarned\": 12544, \"playerTeamID\": 200}, {\"Champ\": \"Briar\", \"kills\": 5, \"deaths\": 9, \"assists\": 5, \"sumName\": \"Shurmima\", \"champLevel\": 14, \"goldEarned\": 10360, \"playerTeamID\": 200}, {\"Champ\": \"Yone\", \"kills\": 5, 
\"deaths\": 11, \"assists\": 4, \"sumName\": \"Wrethesl\", \"champLevel\": 14, \"goldEarned\": 10100, \"playerTeamID\": 200}, {\"Champ\": \"Ezreal\", \"kills\": 7, \"deaths\": 9, \"assists\": 10, \"sumName\": \"MLG Rhitø\", \"champLevel\": 14, \"goldEarned\": 12223, \"playerTeamID\": 200}, {\"Champ\": \"Lux\", \"kills\": 1, \"deaths\": 8, \"assists\": 9, \"sumName\": \"CapTJuiCyFruiTy\", \"champLevel\": 12, \"goldEarned\": 7601, \"playerTeamID\": 200}]"
    }
]